delira/__init__.py
delira/data_loading/__init__.py
delira/data_loading/data_loader.py
delira/data_loading/data_manager.py
delira/data_loading/dataset.py
delira/data_loading/load_utils.py
delira/data_loading/nii.py
delira/data_loading/sampler/__init__.py
delira/data_loading/sampler/abstract_sampler.py
delira/data_loading/sampler/lambda_sampler.py
delira/data_loading/sampler/random_sampler.py
delira/data_loading/sampler/sequential_sampler.py
delira/data_loading/sampler/weighted_sampler.py
delira/io/__init__.py
delira/io/tf.py
delira/io/torch.py
delira/logging/__init__.py
delira/logging/multistream_handler.py
delira/logging/trixi_handler.py
delira/models/__init__.py
delira/models/abstract_network.py
delira/models/classification/ResNet18.py
delira/models/classification/__init__.py
delira/models/classification/classification_network.py
delira/models/classification/classification_network_3D.py
delira/models/classification/classification_network_tf.py
delira/models/gan/__init__.py
delira/models/gan/generative_adversarial_network.py
delira/models/segmentation/__init__.py
delira/models/segmentation/unet.py
delira/training/__init__.py
delira/training/base_trainer.py
delira/training/experiment.py
delira/training/losses.py
delira/training/metrics.py
delira/training/parameters.py
delira/training/predictor.py
delira/training/pytorch_trainer.py
delira/training/tf_trainer.py
delira/training/train_utils.py
delira/training/callbacks/__init__.py
delira/training/callbacks/abstract_callback.py
delira/training/callbacks/early_stopping.py
delira/training/callbacks/pytorch_schedulers.py
delira/utils/__init__.py
delira/utils/config.py
delira/utils/context_managers.py
delira/utils/decorators.py
delira/utils/imageops.py
delira/utils/path.py
delira/utils/time.py
tests/__init__.py
tests/test_dummy.py
tests/data_loading/__init__.py
tests/data_loading/test_data_loader.py
tests/data_loading/test_data_manager.py
tests/data_loading/test_dataset.py
tests/data_loading/test_sampler.py
delira-0.4.0.dist-info/AUTHORS.rst
delira-0.4.0.dist-info/LICENSE
delira-0.4.0.dist-info/METADATA
delira-0.4.0.dist-info/WHEEL
delira-0.4.0.dist-info/top_level.txt
delira-0.4.0.dist-info/RECORD
