Metadata-Version: 2.1
Name: delira
Version: 0.4.0
Summary: UNKNOWN
Home-page: https://github.com/justusschock/delira/
Maintainer: Justus Schock
Maintainer-email: justus.schock@rwth-aachen.de
License: BSD-2
Platform: UNKNOWN
Requires-Python: >=3.5
Requires-Dist: numpy (>=1.15.0)
Requires-Dist: scikit-image (>=0.14.0)
Requires-Dist: scikit-learn (>=0.20.0)
Requires-Dist: jupyter (>=1.0.0)
Requires-Dist: ipython
Requires-Dist: joblib
Requires-Dist: pillow (>=5.4.1)
Requires-Dist: SimpleITK (>=1.1.0)
Requires-Dist: pylint
Requires-Dist: tqdm
Requires-Dist: visdom (>=0.1.8.5)
Requires-Dist: pyyaml
Requires-Dist: trixi-slim (>0.1.2.1)
Requires-Dist: batchgenerators (!=0.19.2,>=0.18.2)
Requires-Dist: psutil
Requires-Dist: nested-lookup
Provides-Extra: full
Requires-Dist: torchvision (>=0.2.1) ; extra == 'full'
Requires-Dist: torch (>=1.0.0) ; extra == 'full'
Requires-Dist: trixi (>0.1.2.1) ; extra == 'full'
Requires-Dist: tensorflow-gpu (==1.13.1) ; extra == 'full'
Requires-Dist: trixi-slim (>0.1.2.1) ; extra == 'full'
Provides-Extra: tensorflow
Requires-Dist: tensorflow-gpu (==1.13.1) ; extra == 'tensorflow'
Requires-Dist: trixi-slim (>0.1.2.1) ; extra == 'tensorflow'
Provides-Extra: torch
Requires-Dist: torchvision (>=0.2.1) ; extra == 'torch'
Requires-Dist: torch (>=1.0.0) ; extra == 'torch'
Requires-Dist: trixi (>0.1.2.1) ; extra == 'torch'
